Metadata-Version: 2.2
Name: uphy-controller
Version: 0.1.0.dev2895
Summary: Add your description here
License: Copyright rt-labs AB, Sweden.
Project-URL: RT-Labs, https://rt-labs.com
Project-URL: U-Phy, https://rt-labs.com/u-phy
Project-URL: Documentation, https://docs.rt-labs.com/u-phy
Requires-Python: >=3.10
License-File: LICENSE.txt
Requires-Dist: dearpygui>=2.0.0
Requires-Dist: pymodbus<3.9.0,>=3.8.3
Requires-Dist: requests>=2.32.3
Requires-Dist: rich>=13.9.2
Requires-Dist: typer>=0.12.5
Requires-Dist: zeroconf>=0.135.0
